pengu/__init__.py
pengu/builders/__init__.py
pengu/builders/augmenter_builder.py
pengu/builders/dataset_builder.py
pengu/builders/model_builder.py
pengu/builders/optimizer_builder.py
pengu/builders/preprocessor_builder.py
pengu/core/__init__.py
pengu/core/csv_core.py
pengu/crawler.py
pengu/data/__init__.py
pengu/data/image_download.py
pengu/data/image_utils.py
pengu/dataset/__init__.py
pengu/dataset/image.py
pengu/dataset/utils.py
pengu/exceptions.py
pengu/main/crawler.py
pengu/main/download.py
pengu/main/make_clf_dataset.py
pengu/main/train_clf.py
pengu/utils/__init__.py
pengu/utils/file_io.py
pengu/utils/function.py
pengu-0.2.0.dist-info/WHEEL
pengu-0.2.0.dist-info/METADATA
pengu-0.2.0.dist-info/RECORD
